griptape_cloud_client/__init__.py
griptape_cloud_client/client.py
griptape_cloud_client/errors.py
griptape_cloud_client/py.typed
griptape_cloud_client/types.py
griptape_cloud_client/api/__init__.py
griptape_cloud_client/api/api_keys/__init__.py
griptape_cloud_client/api/api_keys/create_api_key.py
griptape_cloud_client/api/api_keys/create_organization_api_key.py
griptape_cloud_client/api/api_keys/delete_api_key.py
griptape_cloud_client/api/api_keys/get_api_key.py
griptape_cloud_client/api/api_keys/list_api_keys.py
griptape_cloud_client/api/api_keys/list_organization_api_keys.py
griptape_cloud_client/api/api_keys/update_api_key.py
griptape_cloud_client/api/assets/__init__.py
griptape_cloud_client/api/assets/create_asset.py
griptape_cloud_client/api/assets/create_asset_url.py
griptape_cloud_client/api/assets/delete_asset.py
griptape_cloud_client/api/assets/get_asset.py
griptape_cloud_client/api/assets/list_assets.py
griptape_cloud_client/api/assistant_runs/__init__.py
griptape_cloud_client/api/assistant_runs/cancel_assistant_run.py
griptape_cloud_client/api/assistant_runs/create_assistant_run.py
griptape_cloud_client/api/assistant_runs/get_assistant_run.py
griptape_cloud_client/api/assistant_runs/list_assistant_runs.py
griptape_cloud_client/api/assistants/__init__.py
griptape_cloud_client/api/assistants/create_assistant.py
griptape_cloud_client/api/assistants/delete_assistant.py
griptape_cloud_client/api/assistants/get_assistant.py
griptape_cloud_client/api/assistants/list_assistants.py
griptape_cloud_client/api/assistants/update_assistant.py
griptape_cloud_client/api/billing/__init__.py
griptape_cloud_client/api/billing/create_billing_management_url.py
griptape_cloud_client/api/billing/create_checkout_session.py
griptape_cloud_client/api/buckets/__init__.py
griptape_cloud_client/api/buckets/create_bucket.py
griptape_cloud_client/api/buckets/delete_bucket.py
griptape_cloud_client/api/buckets/get_bucket.py
griptape_cloud_client/api/buckets/list_buckets.py
griptape_cloud_client-0.1.1.dist-info/METADATA
griptape_cloud_client-0.1.1.dist-info/WHEEL
griptape_cloud_client-0.1.1.dist-info/licenses/LICENSE
griptape_cloud_client-0.1.1.dist-info/RECORD
