Metadata-Version: 2.4
Name: griptape-cloud-client
Version: 0.1.1
Summary: Python client for Griptape Cloud API
License-File: LICENSE
Requires-Python: <3.13,>=3.12.0
Requires-Dist: attrs>=22.2.0
Requires-Dist: httpx>=0.28.1
Requires-Dist: python-dateutil>=2.8.0
Requires-Dist: pyyaml>=6.0.3
